{
  "main": {
    "id": "817b90f9863219bc",
    "type": "split",
    "children": [
      {
        "id": "c223a43cb9d14abc",
        "type": "tabs",
        "children": [
          {
            "id": "853ed77015bd70ac",
            "type": "leaf",
            "state": {
              "type": "markdown",
              "state": {
                "file": "prepare for calamity/Game Plan.md",
                "mode": "source",
                "source": false
              },
              "icon": "lucide-file",
              "title": "Game Plan"
            }
          },
          {
            "id": "bdfd6bd4f2724aef",
            "type": "leaf",
            "state": {
              "type": "markdown",
              "state": {
                "file": "prepare for calamity/Tasks to do.md",
                "mode": "source",
                "source": false
              },
              "icon": "lucide-file",
              "title": "Tasks to do"
            }
          },
          {
            "id": "b528efd1d40ea8f6",
            "type": "leaf",
            "state": {
              "type": "markdown",
              "state": {
                "file": "2025-01-23.md",
                "mode": "source",
                "source": false
              },
              "icon": "lucide-file",
              "title": "2025-01-23"
            }
          },
          {
            "id": "c592467b56997f8c",
            "type": "leaf",
            "state": {
              "type": "markdown",
              "state": {
                "file": "prepare for calamity/peoples/person of interest.md",
                "mode": "source",
                "source": false
              },
              "icon": "lucide-file",
              "title": "person of interest"
            }
          },
          {
            "id": "28d111e066227067",
            "type": "leaf",
            "state": {
              "type": "markdown",
              "state": {
                "file": "prepare for calamity/peoples/Todo for Living circumstances.md",
                "mode": "source",
                "source": false
              },
              "icon": "lucide-file",
              "title": "Todo for Living circumstances"
            }
          },
          {
            "id": "e6b7f017348e78df",
            "type": "leaf",
            "state": {
              "type": "image",
              "state": {
                "file": "prepare for calamity/out/collage/outline courses/outline courses.png"
              },
              "icon": "lucide-image",
              "title": "outline courses"
            }
          },
          {
            "id": "58fd0eaace64fb3d",
            "type": "leaf",
            "state": {
              "type": "markdown",
              "state": {
                "file": "prepare for calamity/peoples/person of interest.md",
                "mode": "source",
                "source": false
              },
              "icon": "lucide-file",
              "title": "person of interest"
            }
          },
          {
            "id": "423db1b66737c697",
            "type": "leaf",
            "state": {
              "type": "markdown",
              "state": {
                "file": "prepare for calamity/peoples/Todo for Living circumstances.md",
                "mode": "source",
                "source": false
              },
              "icon": "lucide-file",
              "title": "Todo for Living circumstances"
            }
          },
          {
            "id": "20e893565fb64882",
            "type": "leaf",
            "state": {
              "type": "empty",
              "state": {},
              "icon": "lucide-file",
              "title": "New tab"
            }
          }
        ],
        "currentTab": 2
      }
    ],
    "direction": "vertical"
  },
  "left": {
    "id": "241e4a3228153a70",
    "type": "split",
    "children": [
      {
        "id": "eda24222fe12194b",
        "type": "tabs",
        "children": [
          {
            "id": "1519d39e08493179",
            "type": "leaf",
            "state": {
              "type": "file-explorer",
              "state": {
                "sortOrder": "byModifiedTime"
              },
              "icon": "lucide-folder-closed",
              "title": "Files"
            }
          },
          {
            "id": "981c772747a5cc1e",
            "type": "leaf",
            "state": {
              "type": "search",
              "state": {
                "query": "job",
                "matchingCase": false,
                "explainSearch": false,
                "collapseAll": false,
                "extraContext": false,
                "sortOrder": "alphabetical"
              },
              "icon": "lucide-search",
              "title": "Search"
            }
          },
          {
            "id": "27930df27c9e2924",
            "type": "leaf",
            "state": {
              "type": "bookmarks",
              "state": {},
              "icon": "lucide-bookmark",
              "title": "Bookmarks"
            }
          }
        ]
      }
    ],
    "direction": "horizontal",
    "width": 274.5
  },
  "right": {
    "id": "c98530c0d8c3c35f",
    "type": "split",
    "children": [
      {
        "id": "e19d372a1be8c29d",
        "type": "tabs",
        "children": [
          {
            "id": "5f113b6d36e60987",
            "type": "leaf",
            "state": {
              "type": "backlink",
              "state": {
                "file": "writting.md",
                "collapseAll": false,
                "extraContext": false,
                "sortOrder": "alphabetical",
                "showSearch": false,
                "searchQuery": "",
                "backlinkCollapsed": false,
                "unlinkedCollapsed": true
              },
              "icon": "links-coming-in",
              "title": "Backlinks for writting"
            }
          },
          {
            "id": "9dd6a149f0428346",
            "type": "leaf",
            "state": {
              "type": "outgoing-link",
              "state": {
                "file": "writting.md",
                "linksCollapsed": false,
                "unlinkedCollapsed": true
              },
              "icon": "links-going-out",
              "title": "Outgoing links from writting"
            }
          },
          {
            "id": "234817bda79c2934",
            "type": "leaf",
            "state": {
              "type": "tag",
              "state": {
                "sortOrder": "frequency",
                "useHierarchy": true
              },
              "icon": "lucide-tags",
              "title": "Tags"
            }
          },
          {
            "id": "7c41711a60d63264",
            "type": "leaf",
            "state": {
              "type": "outline",
              "state": {
                "file": "writting.md"
              },
              "icon": "lucide-list",
              "title": "Outline of writting"
            }
          }
        ],
        "currentTab": 3
      }
    ],
    "direction": "horizontal",
    "width": 300,
    "collapsed": true
  },
  "left-ribbon": {
    "hiddenItems": {
      "switcher:Open quick switcher": false,
      "graph:Open graph view": false,
      "canvas:Create new canvas": false,
      "daily-notes:Open today's daily note": false,
      "templates:Insert template": false,
      "command-palette:Open command palette": false
    }
  },
  "active": "b528efd1d40ea8f6",
  "lastOpenFiles": [
    "Untitled 6.canvas",
    "2025-01-23.md",
    "prepare for calamity/Tasks to do.md",
    "prepare for calamity/Todo what to bring and  buy.md",
    "prepare for calamity/making money.md",
    "prepare for calamity/question to ask immigration lawyer.md",
    "prepare for calamity/peoples/Todo for Living circumstances.md",
    "prepare for calamity/peoples/person of interest.md",
    "prepare for calamity/out/collage/outline courses/outline courses.png",
    "prepare for calamity/collage/El Camino College.md",
    "prepare for calamity/Game Plan.md",
    "prepare for calamity/peoples/Untitled.md",
    "emotion.md",
    "Embedded Software Development.md",
    "ielts/16 Writing.md",
    "ielts/17 Writing.md",
    "2024-03-29.md",
    "prepare for calamity/Untitled.md",
    "prepare for calamity/peoples",
    "prepare for calamity/coupon bank and tips.md",
    "prepare for calamity/What to bring.sync-conflict-20250118-223930-XSHLI5C.md",
    "prepare for calamity/food.md",
    "prepare for calamity/phone mobile.md",
    "prepare for calamity/AB 705 Placement Rules with Courses- Updated 07MAY2024- Fall 2024.pdf",
    "prepare for calamity/eebs_flowchartprogram_transferstudents.general.pdf",
    "prepare for calamity/survival/Dumpster driving.md",
    "prepare for calamity/~syncthing~What to bring.md.tmp",
    "prepare for calamity/~syncthing~What to bring.sync-conflict-20250118-223930-XSHLI5C.md.tmp",
    "prepare for calamity/collage/Placement test.md",
    "prepare for calamity/README.md",
    "prepare for calamity/collage/outline courses.md",
    "prepare for calamity/collage/explore the  campus.md",
    "prepare for calamity/Chemistry-Study-Guide.pdf",
    "prepare for calamity/Chemistry-Study-Guide 1.pdf",
    "Pasted image 20250113104611.png",
    "Pasted image 20250113104550.png",
    "prepare for calamity/collage/long beach",
    "Pasted image 20250105184336.png",
    "prepare for calamity/collage/~$ collage 1  transfer electric.pdf",
    "prepare for calamity/collage/los angles  2  transfer computer science.pdf",
    "prepare for calamity/collage/Pasted image 20250103172357.png",
    "Pasted image 20250105184115.png",
    "Pasted image 20241228142748.png",
    "Pasted image 20241206221758.png",
    "BUS savior.PNG",
    "attribute and thier composition.PNG",
    "learing raod map for ielts.canvas",
    "Untitled 5.canvas",
    "Untitled.canvas",
    "Untitled 2.canvas",
    "Untitled 3.canvas",
    "Untitled 4.canvas",
    "Untitled 1.canvas"
  ]
}